{
    "swagger": "2.0",
    "info": {
      "title": "beHome API Service",
      "version": "1.0.0"
    },
    "host": "gw.veep.tech",
    "basePath": "/behome-api/v1",
    "schemes": [
      "http",
      "https"
    ],
    "consumes": [
      "application/json"
    ],
    "produces": [
      "application/json"
    ],
    "paths": {
      "/admin-portal/login": {
        "post": {
          "operationId": "AdminLogin",
          "responses": {
            "200": {
              "description": "A successful response.",
              "schema": {
                "$ref": "#/definitions/pbUserApiResponse"
              }
            }
          },
          "parameters": [
            {
              "name": "body",
              "in": "body",
              "required": true,
              "schema": {
                "$ref": "#/definitions/pbCredentialsLogin"
              }
            }
          ],
          "tags": [
            "BeHomeAuth"
          ]
        }
      },
      "/health": {
        "get": {
          "operationId": "Liveness",
          "responses": {
            "200": {
              "description": "A successful response.",
              "schema": {
                "$ref": "#/definitions/pbLivenessResponse"
              }
            }
          },
          "tags": [
            "BeHomeAuth"
          ]
        }
      },
      "/ready": {
        "get": {
          "operationId": "Readiness",
          "responses": {
            "200": {
              "description": "A successful response.",
              "schema": {
                "$ref": "#/definitions/pbReadinessResponse"
              }
            }
          },
          "tags": [
            "BeHomeAuth"
          ]
        },
        "post": {
          "operationId": "ToggleReadiness",
          "responses": {
            "200": {
              "description": "A successful response.",
              "schema": {
                "$ref": "#/definitions/pbToggleReadinessResponse"
              }
            }
          },
          "tags": [
            "BeHomeAuth"
          ]
        }
      },
      "/user/change_password": {
        "put": {
          "operationId": "ChangePassword",
          "responses": {
            "200": {
              "description": "A successful response.",
              "schema": {
                "$ref": "#/definitions/pbChangePasswordResponse"
              }
            }
          },
          "parameters": [
            {
              "name": "body",
              "in": "body",
              "required": true,
              "schema": {
                "$ref": "#/definitions/pbChangePasswordRequest"
              }
            }
          ],
          "tags": [
            "BeHomeAuth"
          ]
        }
      },
      "/user/confirm_otp": {
        "post": {
          "operationId": "OtpConfirm",
          "responses": {
            "200": {
              "description": "A successful response.",
              "schema": {
                "$ref": "#/definitions/pbOtpConfirmResponse"
              }
            }
          },
          "parameters": [
            {
              "name": "body",
              "in": "body",
              "required": true,
              "schema": {
                "$ref": "#/definitions/pbOtpConfirmRequest"
              }
            }
          ],
          "tags": [
            "BeHomeAuth"
          ]
        }
      },
      "/user/forgot_password": {
        "post": {
          "operationId": "ResetPassword",
          "responses": {
            "200": {
              "description": "A successful response.",
              "schema": {
                "$ref": "#/definitions/pbUserApiResponse"
              }
            }
          },
          "parameters": [
            {
              "name": "body",
              "in": "body",
              "required": true,
              "schema": {
                "$ref": "#/definitions/pbResetPasswordRequest"
              }
            }
          ],
          "tags": [
            "BeHomeAuth"
          ]
        }
      },
      "/user/login": {
        "post": {
          "operationId": "UserLogin",
          "responses": {
            "200": {
              "description": "A successful response.",
              "schema": {
                "$ref": "#/definitions/pbUserApiResponse"
              }
            }
          },
          "parameters": [
            {
              "name": "body",
              "in": "body",
              "required": true,
              "schema": {
                "$ref": "#/definitions/pbCredentialsLogin"
              }
            }
          ],
          "tags": [
            "BeHomeAuth"
          ]
        }
      },
      "/user/logout": {
        "delete": {
          "operationId": "Logout",
          "responses": {
            "200": {
              "description": "A successful response.",
              "schema": {
                "$ref": "#/definitions/pbLogoutResponse"
              }
            }
          },
          "tags": [
            "BeHomeAuth"
          ]
        }
      },
      "/user/me": {
        "get": {
          "summary": "Get user profile",
          "operationId": "Me",
          "responses": {
            "200": {
              "description": "A successful response.",
              "schema": {
                "$ref": "#/definitions/pbUserApiResponse"
              }
            }
          },
          "tags": [
            "BeHomeAuth"
          ]
        }
      },
      "/user/refresh_token": {
        "post": {
          "operationId": "RefreshToken",
          "responses": {
            "200": {
              "description": "A successful response.",
              "schema": {
                "$ref": "#/definitions/pbTokenPair"
              }
            }
          },
          "parameters": [
            {
              "name": "body",
              "in": "body",
              "required": true,
              "schema": {
                "$ref": "#/definitions/pbRefreshTokenRequest"
              }
            }
          ],
          "tags": [
            "BeHomeAuth"
          ]
        }
      },
      "/user/register": {
        "post": {
          "operationId": "Register",
          "responses": {
            "200": {
              "description": "A successful response.",
              "schema": {
                "$ref": "#/definitions/pbUserApiResponse"
              }
            }
          },
          "parameters": [
            {
              "name": "body",
              "in": "body",
              "required": true,
              "schema": {
                "$ref": "#/definitions/pbSignupForm"
              }
            }
          ],
          "tags": [
            "BeHomeAuth"
          ]
        }
      },
      "/user/request_otp": {
        "post": {
          "operationId": "SendOtp",
          "responses": {
            "200": {
              "description": "A successful response.",
              "schema": {
                "$ref": "#/definitions/pbSendOTPResponse"
              }
            }
          },
          "parameters": [
            {
              "name": "body",
              "in": "body",
              "required": true,
              "schema": {
                "$ref": "#/definitions/pbSendOTPRequest"
              }
            }
          ],
          "tags": [
            "BeHomeAuth"
          ]
        }
      },
      "/user/social_auth": {
        "post": {
          "operationId": "SocialAuth",
          "responses": {
            "200": {
              "description": "A successful response.",
              "schema": {
                "$ref": "#/definitions/pbUserApiResponse"
              }
            }
          },
          "parameters": [
            {
              "name": "body",
              "in": "body",
              "required": true,
              "schema": {
                "$ref": "#/definitions/pbSocialAuthRequest"
              }
            }
          ],
          "tags": [
            "BeHomeAuth"
          ]
        }
      },
      "/user/profile/{id}": {
        "put": {
          "operationId": "UpdateProfile",
          "responses": {
            "200": {
              "description": "A successful response.",
              "schema": {
                "$ref": "#/definitions/pbUserUpdateResponse"
              }
            }
          },
          "parameters": [
            {
                "name": "id",
                "in": "path",
                "required": true,
                "type": "string",
                "format": "int64"
            },
            {
              "name": "body",
              "in": "body",
              "required": true,
              "schema": {
                "$ref": "#/definitions/pbUserUpdateRequest"
              }
            }
          ],
          "tags": [
            "BeHomeAuth"
          ]
        }
      },
      "/user/verify_username": {
        "post": {
          "operationId": "VerifyUsername",
          "responses": {
            "200": {
              "description": "A successful response.",
              "schema": {
                "$ref": "#/definitions/pbVerifyUsernameResponse"
              }
            }
          },
          "parameters": [
            {
              "name": "body",
              "in": "body",
              "required": true,
              "schema": {
                "$ref": "#/definitions/pbVerifyUsernameRequest"
              }
            }
          ],
          "tags": [
            "BeHomeAuth"
          ]
        }
      },
     "/cities": {
      "get": {
        "operationId": "GetAllCities",
        "responses": {
          "200": {
            "description": "",
            "schema": {
              "$ref": "#/definitions/pbGetAllCitiesResponse"
            }
          }
        },
        "parameters": [
          {
            "name": "order_by",
            "in": "query",
            "required": false,
            "type": "string"
          },
          {
            "name": "sort_by",
            "in": "query",
            "required": false,
            "type": "string"
          }
        ],
        "tags": [
          "BehomeBackend"
        ]
      },
      "delete": {
        "operationId": "DeleteCity",
        "responses": {
          "200": {
            "description": "",
            "schema": {
              "$ref": "#/definitions/pbDeleteCityResponse"
            }
          }
        },
        "tags": [
          "BehomeBackend"
        ]
      },
      "post": {
        "summary": "service: City",
        "operationId": "CreateCity",
        "responses": {
          "200": {
            "description": "",
            "schema": {
              "$ref": "#/definitions/pbCreateCityResponse"
            }
          }
        },
        "parameters": [
          {
            "name": "body",
            "in": "body",
            "required": true,
            "schema": {
              "$ref": "#/definitions/pbCreateCityRequest"
            }
          }
        ],
        "tags": [
          "BehomeBackend"
        ]
      },
      "put": {
        "operationId": "UpdateCity",
        "responses": {
          "200": {
            "description": "",
            "schema": {
              "$ref": "#/definitions/pbUpdateCityResponse"
            }
          }
        },
        "parameters": [
          {
            "name": "body",
            "in": "body",
            "required": true,
            "schema": {
              "$ref": "#/definitions/pbUpdateCityRequest"
            }
          }
        ],
        "tags": [
          "BehomeBackend"
        ]
      }
    },
    "/countries": {
      "get": {
        "operationId": "GetAllCountries",
        "responses": {
          "200": {
            "description": "",
            "schema": {
              "$ref": "#/definitions/pbGetAllCountriesResponse"
            }
          }
        },
        "parameters": [
          {
            "name": "order_by",
            "in": "query",
            "required": false,
            "type": "string"
          },
          {
            "name": "sort_by",
            "in": "query",
            "required": false,
            "type": "string"
          }
        ],
        "tags": [
          "BehomeBackend"
        ]
      },
      "delete": {
        "operationId": "DeleteCountry",
        "responses": {
          "200": {
            "description": "",
            "schema": {
              "$ref": "#/definitions/pbDeleteCountryResponse"
            }
          }
        },
        "tags": [
          "BehomeBackend"
        ]
      },
      "post": {
        "summary": "service: Country",
        "operationId": "CreateCountry",
        "responses": {
          "200": {
            "description": "",
            "schema": {
              "$ref": "#/definitions/pbCreateCountryResponse"
            }
          }
        },
        "parameters": [
          {
            "name": "body",
            "in": "body",
            "required": true,
            "schema": {
              "$ref": "#/definitions/pbCreateCountryRequest"
            }
          }
        ],
        "tags": [
          "BehomeBackend"
        ]
      },
      "put": {
        "operationId": "UpdateCountry",
        "responses": {
          "200": {
            "description": "",
            "schema": {
              "$ref": "#/definitions/pbUpdateCountryResponse"
            }
          }
        },
        "parameters": [
          {
            "name": "body",
            "in": "body",
            "required": true,
            "schema": {
              "$ref": "#/definitions/pbUpdateCountryRequest"
            }
          }
        ],
        "tags": [
          "BehomeBackend"
        ]
      }
    },
    "/districts": {
      "get": {
        "operationId": "GetDistricts",
        "responses": {
          "200": {
            "description": "",
            "schema": {
              "$ref": "#/definitions/pbGetDistrictsResponse"
            }
          }
        },
        "parameters": [
          {
            "name": "limit",
            "in": "query",
            "required": false,
            "type": "string",
            "format": "int64"
          },
          {
            "name": "offset",
            "in": "query",
            "required": false,
            "type": "string",
            "format": "int64"
          },
          {
            "name": "order_by",
            "in": "query",
            "required": false,
            "type": "string"
          },
          {
            "name": "sort_by",
            "in": "query",
            "required": false,
            "type": "string"
          },
          {
            "name": "ids",
            "in": "query",
            "required": false,
            "type": "array",
            "items": {
              "type": "string",
              "format": "int64"
            }
          },
          {
            "name": "city_id",
            "in": "query",
            "required": false,
            "type": "string",
            "format": "int64"
          },
          {
            "name": "name",
            "in": "query",
            "required": false,
            "type": "string"
          },
          {
            "name": "feature",
            "in": "query",
            "required": false,
            "type": "string",
            "enum": [
              "district_feature_off",
              "district_feature_on"
            ],
            "default": "district_feature_off"
          },
          {
            "name": "status",
            "in": "query",
            "required": false,
            "type": "string",
            "enum": [
              "district_status_disable",
              "district_status_enable"
            ],
            "default": "district_status_disable"
          }
        ],
        "tags": [
          "BehomeBackend"
        ]
      },
      "delete": {
        "operationId": "DeleteDistrict",
        "responses": {
          "200": {
            "description": "",
            "schema": {
              "$ref": "#/definitions/pbDeleteDistrictResponse"
            }
          }
        },
        "tags": [
          "BehomeBackend"
        ]
      },
      "post": {
        "summary": "service: District",
        "operationId": "CreateDistrict",
        "responses": {
          "200": {
            "description": "",
            "schema": {
              "$ref": "#/definitions/pbCreateDistrictResponse"
            }
          }
        },
        "parameters": [
          {
            "name": "body",
            "in": "body",
            "required": true,
            "schema": {
              "$ref": "#/definitions/pbCreateDistrictRequest"
            }
          }
        ],
        "tags": [
          "BehomeBackend"
        ]
      },
      "put": {
        "operationId": "UpdateDistrict",
        "responses": {
          "200": {
            "description": "",
            "schema": {
              "$ref": "#/definitions/pbUpdateDistrictResponse"
            }
          }
        },
        "parameters": [
          {
            "name": "body",
            "in": "body",
            "required": true,
            "schema": {
              "$ref": "#/definitions/pbUpdateDistrictRequest"
            }
          }
        ],
        "tags": [
          "BehomeBackend"
        ]
      }
    },
    "/uploads": {
     
      "post": {
        "summary": "service: Image",
        "operationId": "Uploads",
        "consumes": [multipart/form-data],

        "responses": {
          "200": {
            "description": "",
            "schema": {
              "$ref": "#/definitions/pbCreateImageResponse"
            }
          }
        },
        "parameters": [
          {
            "name": "upfile",
            "type": "file",
            "in": "formData",
            "required": true,
            
          }
        ],
        "tags": [
          "BehomeUpload"
        ]
      },
    
    },
    "/investors": {
      "get": {
        "operationId": "GetAllInvestors",
        "responses": {
          "200": {
            "description": "",
            "schema": {
              "$ref": "#/definitions/pbGetAllInvestorsResponse"
            }
          }
        },
        "parameters": [
          {
            "name": "order_by",
            "in": "query",
            "required": false,
            "type": "string"
          },
          {
            "name": "sort_by",
            "in": "query",
            "required": false,
            "type": "string"
          }
        ],
        "tags": [
          "BehomeBackend"
        ]
      },
      "delete": {
        "operationId": "DeleteInvestor",
        "responses": {
          "200": {
            "description": "",
            "schema": {
              "$ref": "#/definitions/pbDeleteInvestorResponse"
            }
          }
        },
        "tags": [
          "BehomeBackend"
        ]
      },
      "post": {
        "summary": "service: Investor",
        "operationId": "CreateInvestor",
        "responses": {
          "200": {
            "description": "",
            "schema": {
              "$ref": "#/definitions/pbCreateInvestorResponse"
            }
          }
        },
        "parameters": [
          {
            "name": "body",
            "in": "body",
            "required": true,
            "schema": {
              "$ref": "#/definitions/pbCreateInvestorRequest"
            }
          }
        ],
        "tags": [
          "BehomeBackend"
        ]
      },
      "put": {
        "operationId": "UpdateInvestor",
        "responses": {
          "200": {
            "description": "",
            "schema": {
              "$ref": "#/definitions/pbUpdateInvestorResponse"
            }
          }
        },
        "parameters": [
          {
            "name": "body",
            "in": "body",
            "required": true,
            "schema": {
              "$ref": "#/definitions/pbUpdateInvestorRequest"
            }
          }
        ],
        "tags": [
          "BehomeBackend"
        ]
      }
    },
    "/projects": {
      "get": {
        "operationId": "RetrievesAllProjects",
        "responses": {
          "200": {
            "description": "",
            "schema": {
              "$ref": "#/definitions/pbProjectsResponse"
            }
          }
        },
        "parameters": [
          {
            "name": "limit",
            "in": "query",
            "required": false,
            "type": "string",
            "format": "int64"
          },
          {
            "name": "page",
            "in": "query",
            "required": false,
            "type": "string",
            "format": "int64"
          },
          {
            "name": "ids",
            "in": "query",
            "required": false,
            "type": "array",
            "items": {
              "type": "string",
              "format": "int64"
            }
          }
        ],
        "tags": [
          "BehomeBackend"
        ]
      },
      "post": {
        "summary": "service: Project",
        "operationId": "CreateProject",
        "responses": {
          "200": {
            "description": "",
            "schema": {
              "$ref": "#/definitions/pbCreateProjectResponse"
            }
          }
        },
        "parameters": [
          {
            "name": "body",
            "in": "body",
            "required": true,
            "schema": {
              "$ref": "#/definitions/pbProject"
            }
          }
        ],
        "tags": [
          "BehomeBackend"
        ]
      }
    }
    },
    "definitions": {
      "pbApiMetaData": {
        "type": "object",
        "properties": {
          "flag": {
            "type": "string",
            "format": "int64"
          },
          "message": {
            "type": "string"
          }
        },
        "title": "ApiMetaData"
      },
      "pbAuthProvider": {
        "type": "string",
        "enum": [
          "facebook",
          "google"
        ],
        "default": "facebook"
      },
      "pbChangePasswordRequest": {
        "type": "object",
        "properties": {
          "username": {
            "type": "string"
          },
          "input_type": {
            "$ref": "#/definitions/pbInputType"
          },
          "current_password": {
            "type": "string"
          },
          "new_password": {
            "type": "string"
          }
        },
        "title": "ChangePasswordRequest"
      },
      "pbChangePasswordResponse": {
        "type": "object",
        "properties": {
          "meta": {
            "$ref": "#/definitions/pbApiMetaData"
          },
          "data": {
            "$ref": "#/definitions/pbSuccessResponse"
          }
        }
      },
      "pbCredentialsLogin": {
        "type": "object",
        "properties": {
          "username": {
            "type": "string"
          },
          "input_type": {
            "$ref": "#/definitions/pbInputType"
          },
          "password": {
            "type": "string"
          }
        },
        "title": "CredentialsLogin"
      },
      "pbExist": {
        "type": "object",
        "properties": {
          "exist": {
            "type": "boolean",
            "format": "boolean"
          }
        }
      },
      "pbInputType": {
        "type": "string",
        "enum": [
          "phone",
          "email"
        ],
        "default": "phone",
        "description": "`input_type` only has two options: phone or email",
        "title": "input_type"
      },
      "pbLivenessResponse": {
        "type": "object",
        "properties": {
          "message": {
            "type": "string"
          },
          "url": {
            "type": "string"
          }
        },
        "title": "LivenessResponse"
      },
      "pbOTPConfiguration": {
        "type": "object",
        "properties": {
          "limit_sms": {
            "type": "string",
            "format": "int64"
          },
          "limit_call": {
            "type": "string",
            "format": "int64"
          },
          "count_down_sms": {
            "type": "array",
            "items": {
              "type": "string",
              "format": "int64"
            }
          },
          "count_down_call": {
            "type": "array",
            "items": {
              "type": "string",
              "format": "int64"
            }
          }
        },
        "title": "OTPConfiguration"
      },
      "pbLogoutResponse": {
        "type": "object",
        "properties": {
          "meta": {
            "$ref": "#/definitions/pbApiMetaData"
          },
          "data": {
            "$ref": "#/definitions/pbSuccessResponse"
          }
        }
      },
      "pbOtpConfirmRequest": {
        "type": "object",
        "properties": {
          "phone": {
            "type": "string"
          },
          "otp": {
            "type": "string"
          }
        },
        "title": "OtpConfirmRequest"
      },
      "pbOtpConfirmResponse": {
        "type": "object",
        "properties": {
          "meta": {
            "$ref": "#/definitions/pbApiMetaData"
          },
          "data": {
            "$ref": "#/definitions/pbSuccessResponse"
          }
        },
        "title": "OtpConfirmResponse"
      },
      "pbReadinessResponse": {
        "type": "object",
        "properties": {
          "message": {
            "type": "string"
          }
        },
        "title": "ReadinessResponse"
      },
      "pbResetPasswordRequest": {
        "type": "object",
        "properties": {
          "username": {
            "type": "string"
          },
          "input_type": {
            "$ref": "#/definitions/pbInputType"
          },
          "password": {
            "type": "string"
          }
        },
        "title": "ResetPasswordRequest"
      },
      "pbSendOTPData": {
        "type": "object",
        "properties": {
          "total_sent_otp": {
            "type": "string",
            "format": "int64"
          },
          "otp_configuration": {
            "$ref": "#/definitions/pbOTPConfiguration"
          }
        },
        "title": "SendOTPData"
      },
      "pbSendOTPRequest": {
        "type": "object",
        "properties": {
          "phone_no": {
            "type": "string",
            "description": "`phone_no` is user's phone number",
            "title": "phone_no"
          },
          "country_code": {
            "type": "string"
          },
          "type": {
            "$ref": "#/definitions/pbType"
          }
        },
        "title": "SendOTPRequest"
      },
      "pbSendOTPResponse": {
        "type": "object",
        "properties": {
          "meta": {
            "$ref": "#/definitions/pbApiMetaData"
          },
          "data": {
            "$ref": "#/definitions/pbSendOTPData"
          }
        },
        "title": "SendOTPResponse"
      },
      "pbSignupForm": {
        "type": "object",
        "properties": {
          "username": {
            "type": "string"
          },
          "input_type": {
            "$ref": "#/definitions/pbInputType"
          },
          "password": {
            "type": "string"
          }
        },
        "title": "SignupForm"
      },
      "pbSocialAccount": {
        "type": "object",
        "properties": {
          "id": {
            "type": "string",
            "format": "int64"
          },
          "provider": {
            "type": "string"
          },
          "uid": {
            "type": "string"
          },
          "profile_url": {
            "type": "string"
          }
        },
        "title": "SocialUser"
      },
      "pbSocialAuthRequest": {
        "type": "object",
        "properties": {
          "access_token": {
            "type": "string"
          },
          "auth_provider": {
            "$ref": "#/definitions/pbAuthProvider"
          }
        },
        "title": "SocialAuth"
      },
      "pbSuccessResponse": {
        "type": "object",
        "properties": {
          "success": {
            "type": "boolean",
            "format": "boolean"
          }
        }
      },
      "pbToggleReadinessResponse": {
        "type": "object",
        "properties": {
          "message": {
            "type": "string"
          }
        },
        "title": "ToggleReadinessResponse"
      },
      "pbTokenPair": {
        "type": "object",
        "properties": {
          "access_token": {
            "type": "string"
          },
          "refresh_token": {
            "type": "string"
          }
        },
        "title": "TokenPair"
      },
      "pbType": {
        "type": "string",
        "enum": [
          "sms",
          "call"
        ],
        "default": "sms",
        "description": "`type` is kind of opt request type, just only two options: sms or call",
        "title": "type"
      },
      "pbUser": {
        "type": "object",
        "properties": {
          "id": {
            "type": "string",
            "format": "int64"
          },
          "name": {
            "type": "string"
          },
          "first_name": {
            "type": "string"
          },
          "last_name": {
            "type": "string"
          },
          "phone": {
            "type": "string"
          },
          "email": {
            "type": "string"
          },
          "role": {
            "type": "string"
          },
          "identity_no": {
            "type": "string"
          },
          "age": {
            "type": "string"
          },
          "address": {
            "type": "string"
          },
          "apartment": {
            "type": "string"
          },
          "city": {
            "type": "string"
          },
          "province_code": {
            "type": "string"
          },
          "country": {
            "type": "string"
          },
          "country_code": {
            "type": "string"
          },
          "avatar": {
            "type": "string"
          },
          "created_at": {
            "type": "string"
          },
          "updated_at": {
            "type": "string"
          },
          "enabled": {
            "type": "boolean",
            "format": "boolean"
          },
          "device_token": {
            "type": "string"
          },
          "social_account": {
            "$ref": "#/definitions/pbSocialAccount"
          }
        },
        "title": "User"
      },
      "pbUserApiResponse": {
        "type": "object",
        "properties": {
          "meta": {
            "$ref": "#/definitions/pbApiMetaData"
          },
          "data": {
            "$ref": "#/definitions/pbUserData"
          }
        },
        "title": "UserApiResponse"
      },
      "pbUserData": {
        "type": "object",
        "properties": {
          "access_token": {
            "type": "string"
          },
          "refresh_token": {
            "type": "string"
          },
          "user": {
            "$ref": "#/definitions/pbUser"
          }
        },
        "title": "UserData"
      },
      "pbVerifyUsernameRequest": {
        "type": "object",
        "properties": {
          "username": {
            "type": "string",
            "description": "`username` of user",
            "title": "username"
          },
          "input_type": {
            "$ref": "#/definitions/pbInputType"
          }
        },
        "title": "VerifyUsernameRequest"
      },
      "pbVerifyUsernameResponse": {
        "type": "object",
        "properties": {
          "meta": {
            "$ref": "#/definitions/pbApiMetaData"
          },
          "data": {
            "$ref": "#/definitions/pbExist",
            "description": "if user is existing on database =\u003e  exist = true",
            "title": "exist"
          }
        },
        "title": "VerifyUsernameResponse"
      },
       "pbUserUpdateRequest": {
        "type": "object",
        "properties": {
          "name": {
            "type": "string"
          },
          "first_name": {
            "type": "string"
          },
          "last_name": {
            "type": "string"
          },
          "phone": {
            "type": "string"
          },
          "email": {
            "type": "string"
          },
          "identity_no": {
            "type": "string"
          },
          "age": {
            "type": "string",
            "format": "int64"
          },
          "address": {
            "type": "string"
          },
          "apartment": {
            "type": "string"
          },
          "city": {
            "type": "string"
          },
          "province_code": {
            "type": "string"
          },
          "country": {
            "type": "string"
          },
          "country_code": {
            "type": "string"
          },
          "avatar": {
            "type": "string"
          },
          "device_token": {
            "type": "string"
          },
          "gender": {
            "type": "string",
            "format": "int64",
            "enum": [-1, 0, 1] 
          }
        }
     
    },
    "pbUserUpdateResponse": {
        "type": "object",
        "properties": {
          "meta": {
            "$ref": "#/definitions/pbApiMetaData"
          },
          "data": {
            "$ref": "#/definitions/pbUserUpdateData"
          }
        }
    },
    "pbUserUpdateData": {
      "type": "object",
      "properties": {
        "user": {
          "$ref": "#/definitions/pbUser"
        }
      }
    },
    "pbRefreshTokenRequest": {
      "type": "object",
      "properties": {
        "refresh_token": {
          "type": "string",
          "title": "refresh_token"
        }
      },
      "title": "RefreshTokenRequest"
    },
     "pbCitiesData": {
      "type": "object",
      "properties": {
        "cities": {
          "type": "array",
          "items": {
            "$ref": "#/definitions/pbCity"
          }
        },
        "count": {
          "type": "string",
          "format": "int64"
        }
      }
    },
    "pbCity": {
      "type": "object",
      "properties": {
        "id": {
          "type": "string",
          "format": "int64"
        },
        "country_id": {
          "type": "string",
          "format": "int64"
        },
        "name": {
          "type": "string"
        },
        "code": {
          "type": "string"
        },
        "feature": {
          "$ref": "#/definitions/pbCityFeature"
        },
        "order": {
          "type": "string",
          "format": "int64"
        },
        "status": {
          "$ref": "#/definitions/pbCityStatus"
        }
      },
      "title": "City"
    },
    "pbCityData": {
      "type": "object",
      "properties": {
        "city": {
          "$ref": "#/definitions/pbCity"
        }
      }
    },
    "pbCityFeature": {
      "type": "string",
      "enum": [
        "city_feature_off",
        "city_feature_on"
      ],
      "default": "city_feature_off",
      "description": "`city_feature` only has two options: on or off",
      "title": "city_feature"
    },
    "pbCityInput": {
      "type": "object",
      "properties": {
        "country_id": {
          "type": "string",
          "format": "int64"
        },
        "name": {
          "type": "string"
        },
        "code": {
          "type": "string"
        },
        "feature": {
          "$ref": "#/definitions/pbCityFeature"
        },
        "order": {
          "type": "string",
          "format": "int64"
        },
        "status": {
          "$ref": "#/definitions/pbCityStatus"
        }
      }
    },
    "pbCityStatus": {
      "type": "string",
      "enum": [
        "city_status_disable",
        "city_status_enable"
      ],
      "default": "city_status_disable",
      "description": "`city_status` only has two options: enable or disable",
      "title": "city_status"
    },
    "pbCountriesData": {
      "type": "object",
      "properties": {
        "countries": {
          "type": "array",
          "items": {
            "$ref": "#/definitions/pbCountry"
          }
        },
        "count": {
          "type": "string",
          "format": "int64"
        }
      }
    },
    "pbCountry": {
      "type": "object",
      "properties": {
        "id": {
          "type": "string",
          "format": "int64"
        },
        "name": {
          "type": "string"
        },
        "code": {
          "type": "string"
        },
        "feature": {
          "$ref": "#/definitions/pbCountryFeature"
        },
        "order": {
          "type": "string",
          "format": "int64"
        },
        "status": {
          "$ref": "#/definitions/pbCountryStatus"
        }
      },
      "title": "Country"
    },
    "pbCountryData": {
      "type": "object",
      "properties": {
        "country": {
          "$ref": "#/definitions/pbCountry"
        }
      }
    },
    "pbCountryFeature": {
      "type": "string",
      "enum": [
        "country_feature_off",
        "country_feature_on"
      ],
      "default": "country_feature_off",
      "description": "`country_feature` only has two options: on or off",
      "title": "country_feature"
    },
    "pbCountryInput": {
      "type": "object",
      "properties": {
        "name": {
          "type": "string"
        },
        "code": {
          "type": "string"
        },
        "feature": {
          "$ref": "#/definitions/pbCountryFeature"
        },
        "order": {
          "type": "string",
          "format": "int64"
        },
        "status": {
          "$ref": "#/definitions/pbCountryStatus"
        }
      }
    },
    "pbCountryStatus": {
      "type": "string",
      "enum": [
        "country_status_disable",
        "country_status_enable"
      ],
      "default": "country_status_disable",
      "description": "`country_status` only has two options: enable or disable",
      "title": "country_status"
    },
    "pbCreateCityRequest": {
      "type": "object",
      "properties": {
        "city_input": {
          "$ref": "#/definitions/pbCityInput"
        }
      }
    },
    "pbCreateCityResponse": {
      "type": "object",
      "properties": {
        "meta": {
          "$ref": "#/definitions/pbMetaData"
        },
        "data": {
          "$ref": "#/definitions/pbCityData"
        }
      }
    },
    "pbCreateCountryRequest": {
      "type": "object",
      "properties": {
        "country_input": {
          "$ref": "#/definitions/pbCountryInput"
        }
      }
    },
    "pbCreateCountryResponse": {
      "type": "object",
      "properties": {
        "meta": {
          "$ref": "#/definitions/pbMetaData"
        },
        "data": {
          "$ref": "#/definitions/pbCountryData"
        }
      }
    },
    "pbCreateDistrictRequest": {
      "type": "object",
      "properties": {
        "district_input": {
          "$ref": "#/definitions/pbDistrictInput"
        }
      }
    },
    "pbCreateDistrictResponse": {
      "type": "object",
      "properties": {
        "meta": {
          "$ref": "#/definitions/pbMetaData"
        },
        "data": {
          "$ref": "#/definitions/pbDistrictData"
        }
      }
    },
    "pbCreateImageRequest": {
      "type": "object",
      "properties": {
        "image_input": {
          "$ref": "#/definitions/pbImageInput"
        }
      }
    },
    "pbCreateImageResponse": {
      "type": "object",
      "properties": {
        "meta": {
          "$ref": "#/definitions/pbMetaData"
        },
        "data": {
          "$ref": "#/definitions/pbImageData"
        }
      }
    },
    "pbCreateInvestorRequest": {
      "type": "object",
      "properties": {
        "investor_input": {
          "$ref": "#/definitions/pbInvestorInput"
        }
      }
    },
    "pbCreateInvestorResponse": {
      "type": "object",
      "properties": {
        "meta": {
          "$ref": "#/definitions/pbMetaData"
        },
        "data": {
          "$ref": "#/definitions/pbInvestorData"
        }
      }
    },
    "pbCreateProjectResponse": {
      "type": "object",
      "properties": {
        "meta": {
          "$ref": "#/definitions/pbMetaData"
        },
        "project": {
          "$ref": "#/definitions/pbProject"
        }
      }
    },
    "pbDeleteCityResponse": {
      "type": "object"
    },
    "pbDeleteCountryResponse": {
      "type": "object",
      "properties": {
        "meta": {
          "$ref": "#/definitions/pbMetaData"
        }
      }
    },
    "pbDeleteDistrictResponse": {
      "type": "object"
    },
    "pbDeleteImageResponse": {
      "type": "object",
      "properties": {
        "meta": {
          "$ref": "#/definitions/pbMetaData"
        }
      }
    },
    "pbDeleteInvestorResponse": {
      "type": "object"
    },
    "pbDistrict": {
      "type": "object",
      "properties": {
        "id": {
          "type": "string",
          "format": "int64"
        },
        "city_id": {
          "type": "string",
          "format": "int64"
        },
        "name": {
          "type": "string"
        },
        "feature": {
          "$ref": "#/definitions/pbDistrictFeature"
        },
        "order": {
          "type": "string",
          "format": "int64"
        },
        "status": {
          "$ref": "#/definitions/pbDistrictStatus"
        }
      },
      "title": "Distric"
    },
    "pbDistrictData": {
      "type": "object",
      "properties": {
        "district": {
          "$ref": "#/definitions/pbDistrict"
        }
      }
    },
    "pbDistrictFeature": {
      "type": "string",
      "enum": [
        "district_feature_off",
        "district_feature_on"
      ],
      "default": "district_feature_off",
      "description": "`district_feature` only has two options: on or off",
      "title": "district_feature"
    },
    "pbDistrictInput": {
      "type": "object",
      "properties": {
        "city_id": {
          "type": "string",
          "format": "int64"
        },
        "name": {
          "type": "string"
        },
        "feature": {
          "$ref": "#/definitions/pbDistrictFeature"
        },
        "order": {
          "type": "string",
          "format": "int64"
        },
        "status": {
          "$ref": "#/definitions/pbDistrictStatus"
        }
      }
    },
    "pbDistrictStatus": {
      "type": "string",
      "enum": [
        "district_status_disable",
        "district_status_enable"
      ],
      "default": "district_status_disable",
      "description": "`district_status` only has two options: enable or disable",
      "title": "district_status"
    },
    "pbDistrictsData": {
      "type": "object",
      "properties": {
        "districts": {
          "type": "array",
          "items": {
            "$ref": "#/definitions/pbDistrict"
          }
        },
        "count": {
          "type": "string",
          "format": "int64"
        }
      }
    },
    "pbGetAllCitiesResponse": {
      "type": "object",
      "properties": {
        "meta": {
          "$ref": "#/definitions/pbMetaData"
        },
        "data": {
          "$ref": "#/definitions/pbCitiesData"
        }
      }
    },
    "pbGetAllCountriesResponse": {
      "type": "object",
      "properties": {
        "meta": {
          "$ref": "#/definitions/pbMetaData"
        },
        "data": {
          "$ref": "#/definitions/pbCountriesData"
        }
      }
    },
    "pbGetAllInvestorsResponse": {
      "type": "object",
      "properties": {
        "meta": {
          "$ref": "#/definitions/pbMetaData"
        },
        "data": {
          "$ref": "#/definitions/pbInvestorsData"
        }
      }
    },
    "pbGetCitiesResponse": {
      "type": "object",
      "properties": {
        "meta": {
          "$ref": "#/definitions/pbMetaData"
        },
        "data": {
          "$ref": "#/definitions/pbCitiesData"
        }
      }
    },
    "pbGetCitiesVNResponse": {
      "type": "object",
      "properties": {
        "meta": {
          "$ref": "#/definitions/pbMetaData"
        },
        "data": {
          "$ref": "#/definitions/pbCitiesData"
        }
      }
    },
    "pbGetCityResponse": {
      "type": "object",
      "properties": {
        "meta": {
          "$ref": "#/definitions/pbMetaData"
        },
        "data": {
          "$ref": "#/definitions/pbCityData"
        }
      }
    },
    "pbGetCountriesResponse": {
      "type": "object",
      "properties": {
        "meta": {
          "$ref": "#/definitions/pbMetaData"
        },
        "data": {
          "$ref": "#/definitions/pbCountriesData"
        }
      }
    },
    "pbGetCountryResponse": {
      "type": "object",
      "properties": {
        "meta": {
          "$ref": "#/definitions/pbMetaData"
        },
        "data": {
          "$ref": "#/definitions/pbCountryData"
        }
      }
    },
    "pbGetDistrictResponse": {
      "type": "object",
      "properties": {
        "meta": {
          "$ref": "#/definitions/pbMetaData"
        },
        "data": {
          "$ref": "#/definitions/pbDistrictData"
        }
      }
    },
    "pbGetDistrictsResponse": {
      "type": "object",
      "properties": {
        "meta": {
          "$ref": "#/definitions/pbMetaData"
        },
        "data": {
          "$ref": "#/definitions/pbDistrictsData"
        }
      }
    },
    "pbGetImageResponse": {
      "type": "object",
      "properties": {
        "meta": {
          "$ref": "#/definitions/pbMetaData"
        },
        "data": {
          "$ref": "#/definitions/pbImageData"
        }
      }
    },
    "pbGetImagesResponse": {
      "type": "object",
      "properties": {
        "meta": {
          "$ref": "#/definitions/pbMetaData"
        },
        "data": {
          "$ref": "#/definitions/pbImagesData"
        }
      }
    },
    "pbGetInvestorResponse": {
      "type": "object",
      "properties": {
        "meta": {
          "$ref": "#/definitions/pbMetaData"
        },
        "data": {
          "$ref": "#/definitions/pbInvestorData"
        }
      }
    },
    "pbGetInvestorsResponse": {
      "type": "object",
      "properties": {
        "meta": {
          "$ref": "#/definitions/pbMetaData"
        },
        "data": {
          "$ref": "#/definitions/pbInvestorsData"
        }
      }
    },
    "pbImage": {
      "type": "object",
      "properties": {
        "id": {
          "type": "string",
          "format": "int64"
        },
        "title": {
          "type": "string"
        },
        "tag": {
          "type": "string"
        },
        "user_id": {
          "type": "string"
        },
        "object": {
          "type": "string"
        },
        "object_id": {
          "type": "string"
        },
        "details": {
          "type": "array",
          "items": {
            "$ref": "#/definitions/pbImageDetail"
          }
        }
      },
      "title": "Image"
    },
    "pbImageData": {
      "type": "object",
      "properties": {
        "image": {
          "$ref": "#/definitions/pbImage"
        }
      }
    },
    "pbImageDetail": {
      "type": "object",
      "properties": {
        "id": {
          "type": "string",
          "format": "int64"
        },
        "image_id": {
          "type": "string",
          "format": "int64"
        },
        "size": {
          "type": "string"
        },
        "type": {
          "type": "string"
        },
        "path": {
          "type": "string"
        }
      }
    },
    "pbImageDetailInput": {
      "type": "object",
      "properties": {
        "image_id": {
          "type": "string",
          "format": "int64"
        },
        "size": {
          "type": "string"
        },
        "type": {
          "type": "string"
        },
        "path": {
          "type": "string"
        }
      }
    },
    "pbImageInput": {
      "type": "object",
      "properties": {
        "title": {
          "type": "string"
        },
        "tag": {
          "type": "string"
        },
        "details": {
          "type": "array",
          "items": {
            "$ref": "#/definitions/pbImageDetailInput"
          }
        }
      }
    },
    "pbImagesData": {
      "type": "object",
      "properties": {
        "images": {
          "type": "array",
          "items": {
            "$ref": "#/definitions/pbImage"
          }
        },
        "count": {
          "type": "string",
          "format": "int64"
        }
      }
    },
    "pbInvestor": {
      "type": "object",
      "properties": {
        "id": {
          "type": "string"
        },
        "name": {
          "type": "string"
        },
        "feature": {
          "$ref": "#/definitions/pbInvestorFeature"
        },
        "status": {
          "$ref": "#/definitions/pbInvestorStatus"
        }
      },
      "title": "Investor"
    },
    "pbInvestorData": {
      "type": "object",
      "properties": {
        "investor": {
          "$ref": "#/definitions/pbInvestor"
        }
      }
    },
    "pbInvestorFeature": {
      "type": "string",
      "enum": [
        "investor_feature_off",
        "investor_feature_on"
      ],
      "default": "investor_feature_off",
      "description": "`investor_feature` only has two options: on or off",
      "title": "investor_feature"
    },
    "pbInvestorInput": {
      "type": "object",
      "properties": {
        "name": {
          "type": "string"
        },
        "feature": {
          "$ref": "#/definitions/pbInvestorFeature"
        },
        "status": {
          "$ref": "#/definitions/pbInvestorStatus"
        }
      }
    },
    "pbInvestorStatus": {
      "type": "string",
      "enum": [
        "investor_status_disable",
        "investor_status_enable"
      ],
      "default": "investor_status_disable",
      "description": "`investor_status` only has two options: enable or disable",
      "title": "investor_status"
    },
    "pbInvestorsData": {
      "type": "object",
      "properties": {
        "investors": {
          "type": "array",
          "items": {
            "$ref": "#/definitions/pbInvestor"
          }
        },
        "count": {
          "type": "string",
          "format": "int64"
        }
      }
    },
    "pbMetaData": {
      "type": "object",
      "properties": {
        "flag": {
          "type": "string",
          "format": "int64"
        },
        "message": {
          "type": "string"
        }
      }
    },
    "pbProject": {
      "type": "object",
      "properties": {
        "project_id": {
          "type": "string",
          "format": "int64"
        },
        "type_of_property": {
          "type": "string"
        },
        "investor_id": {
          "type": "string",
          "format": "int64"
        },
        "project_name": {
          "type": "string"
        },
        "acreage": {
          "type": "number",
          "format": "double"
        },
        "description": {
          "type": "string"
        },
        "number_of_flats": {
          "type": "string",
          "format": "int64"
        },
        "address": {
          "type": "string"
        },
        "city_id": {
          "type": "string",
          "format": "int64"
        },
        "district_id": {
          "type": "string",
          "format": "int64"
        },
        "ward_id": {
          "type": "string",
          "format": "int64"
        },
        "created_at": {
          "type": "string"
        },
        "updated_at": {
          "type": "string"
        }
      }
    },
    "pbProjectData": {
      "type": "object",
      "properties": {
        "projects": {
          "type": "array",
          "items": {
            "$ref": "#/definitions/pbProject"
          }
        },
        "count": {
          "type": "string",
          "format": "int64"
        }
      }
    },
    "pbProjectsResponse": {
      "type": "object",
      "properties": {
        "meta": {
          "$ref": "#/definitions/pbMetaData"
        },
        "data": {
          "$ref": "#/definitions/pbProjectData"
        }
      }
    },
    "pbUpdateCityRequest": {
      "type": "object",
      "properties": {
        "city": {
          "$ref": "#/definitions/pbCity"
        }
      }
    },
    "pbUpdateCityResponse": {
      "type": "object",
      "properties": {
        "meta": {
          "$ref": "#/definitions/pbMetaData"
        },
        "data": {
          "$ref": "#/definitions/pbCityData"
        }
      }
    },
    "pbUpdateCountryRequest": {
      "type": "object",
      "properties": {
        "country": {
          "$ref": "#/definitions/pbCountry"
        }
      }
    },
    "pbUpdateCountryResponse": {
      "type": "object",
      "properties": {
        "meta": {
          "$ref": "#/definitions/pbMetaData"
        },
        "data": {
          "$ref": "#/definitions/pbCountryData"
        }
      }
    },
    "pbUpdateDistrictRequest": {
      "type": "object",
      "properties": {
        "district": {
          "$ref": "#/definitions/pbDistrict"
        }
      }
    },
    "pbUpdateDistrictResponse": {
      "type": "object",
      "properties": {
        "meta": {
          "$ref": "#/definitions/pbMetaData"
        },
        "data": {
          "$ref": "#/definitions/pbDistrictData"
        }
      }
    },
    "pbUpdateImageRequest": {
      "type": "object",
      "properties": {
        "image": {
          "$ref": "#/definitions/pbImage"
        }
      }
    },
    "pbUpdateImageResponse": {
      "type": "object",
      "properties": {
        "meta": {
          "$ref": "#/definitions/pbMetaData"
        },
        "data": {
          "$ref": "#/definitions/pbImageData"
        }
      }
    },
    "pbUpdateInvestorRequest": {
      "type": "object",
      "properties": {
        "investor": {
          "$ref": "#/definitions/pbInvestor"
        }
      }
    },
    "pbUpdateInvestorResponse": {
      "type": "object",
      "properties": {
        "meta": {
          "$ref": "#/definitions/pbMetaData"
        },
        "data": {
          "$ref": "#/definitions/pbInvestorData"
        }
      }
    },
    "pbVersionResponse": {
      "type": "object",
      "properties": {
        "version": {
          "type": "string"
        }
      }
    }
  
    },
    "securityDefinitions": {
      "BasicAuth": {
        "type": "apiKey",
        "name": "Authorizations",
        "in": "header"
      }
    }
  }
  
